particle_pack_tools-0.0.6.dist-info/licenses/LICENSE
pptools/__init__.py
pptools/io.py
pptools/preprocess.py
pptools/visualize.py
particle_pack_tools-0.0.6.dist-info/METADATA
particle_pack_tools-0.0.6.dist-info/WHEEL
particle_pack_tools-0.0.6.dist-info/top_level.txt
particle_pack_tools-0.0.6.dist-info/RECORD
